CHANGELOG.md
MANIFEST.in
README.md
fabvenv.py
setup.py
fabvenv.egg-info/PKG-INFO
fabvenv.egg-info/SOURCES.txt
fabvenv.egg-info/dependency_links.txt
fabvenv.egg-info/top_level.txt