Metadata-Version: 1.1
Name: fabvenv
Version: 0.2.1
Summary: A fabric utility for creating remote virtual environments, and installing and updating packages.
Home-page: https://github.com/todddeluca/fabvenv
Author: Todd Francis DeLuca
Author-email: todddeluca@yahoo.com
License: MIT
Keywords: fabric virtualenv venv utility
Platform: UNKNOWN
Classifier: License :: OSI Approved :: MIT License
Classifier: Development Status :: 3 - Alpha
Classifier: Programming Language :: Python :: 2
Classifier: Programming Language :: Python :: 2.7
